fastapi_openapi_parser/OpenApiParser.py
fastapi_openapi_parser/__init__.py
fastapi_openapi_parser-1.0.1.dist-info/LICENSE
fastapi_openapi_parser-1.0.1.dist-info/METADATA
fastapi_openapi_parser-1.0.1.dist-info/WHEEL
fastapi_openapi_parser-1.0.1.dist-info/RECORD
