Metadata-Version: 2.1
Name: fastapi-openapi-parser
Version: 1.0.1
Summary: 
Home-page: https://github.com/xitowzys-ISZF/FastAPI-OpenAPI-Parser
License: Apache-2.0
Keywords: python,fastapi,gateway,api,microservice,microservices
Author: Kalinka George
Author-email: xitowzys@gmail.com
Requires-Python: >=3.11,<4.0
Classifier: License :: OSI Approved :: Apache Software License
Classifier: Programming Language :: Python :: 3
Classifier: Programming Language :: Python :: 3.11
Requires-Dist: requests (>=2.28.2,<3.0.0)
Project-URL: Repository, https://github.com/xitowzys-ISZF/FastAPI-OpenAPI-Parser
